qmenta/__init__.py
qmenta/core/.gitignore
qmenta/core/__init__.py
qmenta/core/auth.py
qmenta/core/errors.py
qmenta/core/platform.py
qmenta/core/upload/__init__.py
qmenta/core/upload/multi.py
qmenta/core/upload/prepare.py
qmenta/core/upload/single.py
qmenta/py.typed
qmenta_core-4.0.2.dist-info/METADATA
qmenta_core-4.0.2.dist-info/WHEEL
qmenta_core-4.0.2.dist-info/entry_points.txt
qmenta_core-4.0.2.dist-info/RECORD
