Metadata-Version: 2.1
Name: qmenta-core
Version: 4.0.2
Summary: QMENTA core library to communicate with the QMENTA platform.
Home-page: https://www.qmenta.com/
License: Proprietary
Author: QMENTA
Author-email: dev@qmenta.com
Requires-Python: >=3.10,<4.0
Classifier: Development Status :: 4 - Beta
Classifier: Intended Audience :: Developers
Classifier: License :: Other/Proprietary License
Classifier: Programming Language :: Python :: 3
Classifier: Programming Language :: Python :: 3.10
Classifier: Programming Language :: Python :: 3.11
Classifier: Programming Language :: Python :: 3.12
Requires-Dist: blinker (>=1.4,<2.0)
Requires-Dist: importlib-metadata (>=6.8.0,<7.0.0)
Requires-Dist: python-dotenv (>=1.0.0,<2.0.0)
Requires-Dist: pyyaml (>=6.0.1,<7.0.0)
Requires-Dist: qmenta-anon (>=2.0,<3.0)
Requires-Dist: requests (>=2.31.0,<3.0.0)
Requires-Dist: xdg (>=6.0.0,<7.0.0)
Project-URL: Documentation, https://docs.qmenta.com/core/
